fybrik_python_transformation/__init__.py
fybrik_python_transformation-0.2.1.dist-info/METADATA
fybrik_python_transformation-0.2.1.dist-info/WHEEL
fybrik_python_transformation-0.2.1.dist-info/top_level.txt
fybrik_python_transformation-0.2.1.dist-info/RECORD
